{
    "CC":         {"name": "Character Count",                                   "range": [18269.02, 84689.45000000013]},
    "CW":         {"name": "Word Count",                                        "range": [2984.0, 13609.080000000002]},
    "CSN":        {"name": "Sentence Count",                                    "range": [143.0, 665.0]},
    "CS":         {"name": "Section Count",                                     "range": [5.0, 14.0]},
    "CMSL":       {"name": "Mean Section Length",                               "range": [3122.9225, 13480.42416666667]},
    "CP":         {"name": "Paragraph Count",                                   "range": [29.0, 143.01000000000022]},
    "CMPL":       {"name": "Mean Paragraph Length",                             "range": [582.6118235294117, 1039.8639423076927]},
    "CLSL":       {"name": "Largest Section Length",                            "range": [6434.0, 43135.69000000002]},
    "CSSL":       {"name": "Shortest Section Length",                           "range": [783.6700000000001, 3231.0200000000004]},
    "CSTDSL":     {"name": "Standard Deviation of Section Length",              "range": [2023.922750291074, 16664.03475697945]}, 
    "CLSSR":      {"name": "Longest-Shortest Section Ratio",                    "range": [5.608087595980126, 5543.960000000043]}, 
    "CB":         {"name": "Subsection Count",                                  "range": [3.0, 26.0]},
    "CBPS":       {"name": "Subsections per Section",                           "range": [0.5714285714285714, 3.75]},
    "CNL":        {"name": "Introduction Length",                               "range": [1639.0, 4106.050000000001]},
    "CNLTLR":     {"name": "Introduction Length-Text Length Ratio",             "range": [0.06540481273000737, 0.19040063376651797]},
    "CR":         {"name": "Reference Count",                                   "range": [32.0, 315.02000000000044]},
    "CCC":        {"name": "Citation Count",                                    "range": [56.0, 485.0100000000002]},
    "CCCPC":      {"name": "Citations per Character",                           "range": [0.0030839944262863956, 0.011035545105318005]},
    "CCCPS":      {"name": "Citations per Section",                             "range": [10.0, 68.80200000000004]},
    "CEL":        {"name": "External Link Count",                               "range": [0.0, 29.0]},
    "CELPS":      {"name": "External Links per Section",                        "range": [0.0, 4.334000000000015]},
    "CIL":        {"name": "Internal Link Count",                               "range": [126.0, 691.0300000000007]},
    "CI":         {"name": "Image Count",                                       "range": [4.0, 37.0]},
    "CIPS":       {"name": "Images per Section",                                "range": [0.6, 5.4]},
    "CIB":        {"name": "Number of Information Boxes",                       "range": [1.0, 6.0]},
    "CCT":        {"name": "Number of Citation Templates",                      "range": [26.0, 287.0100000000002]},
    "CNCT":       {"name": "Number of Non-Citation Templates",                  "range": [41.67000000000007, 548.0200000000004]},
    "CTB":        {"name": "Number of Unique Templates",                        "range": [0.0, 8.0]},
    "CUCT":       {"name": "Number of Tables",                                  "range": [22.0, 74.0]},
    "SSLS":       {"name": "Largest Sentence Size",                             "range": [60.0, 647.0500000000011]},
    "SSSS":       {"name": "Shortest Sentence Size",                            "range": [2.0, 10.0]},
    "SMSS":       {"name": "Mean Sentence Size",                                "range": [22.23076923076923, 39.08672739244954]},
    "SLSR":       {"name": "Large Sentence Rate",                               "range": [0.137542953313237, 0.24509988901220867]},
    "SSSR":       {"name": "Short Sentence Rate",                               "range": [0.33707865168539325, 0.6412242546449661]},
    "SS":         {"name": "Syllable Count",                                    "range": [4994.0, 22940.27000000003]},
    "SMSPW":      {"name": "Mean Number of Syllables per Word",                 "range": [1.6592658863863843, 1.9438451469919669]},
    "SMCPW":      {"name": "Mean Number of Characters per Word",                "range": [4.912545653748391, 5.561857775971481]},
    "SWL6":       {"name": "Number of Words Larger than 6 Letters",             "range": [799.0, 3953.050000000001]},
    "HA":         {"name": "Age (days)",                                        "range": [5445.02, 7616.0]},
    "HAPR":       {"name": "Age per Review",                                    "range": [5.237270788013693, 36.63418168964298]},
    "HRPD":       {"name": "Reviews per Day",                                   "range": [0.08261613004841813, 1.8071422430433903]},
    "HRPC":       {"name": "Reviews per Contributor",                           "range": [2.606259698617534, 12.546415094339643]},
    "HRPCSD":     {"name": "Reviews per Contributor Standard Deviation",        "range": [10.957810210039062, 88.18999006268409]},
    "HR":         {"name": "Review Count",                                      "range": [416.0, 12101.530000000033]},
    "HC":         {"name": "Contributor Count",                                 "range": [114.0, 4171.370000000008]},
    "HRC":        {"name": "Registered Contributor Count",                      "range": [91.0, 2045.1900000000041]},
    "HAC":        {"name": "Anonymous Contributor Count",                       "range": [22.0, 2151.190000000004]},
    "HRCPC":      {"name": "Registered Contributors per Contributor",           "range": [0.6526802600472814, 0.9818245614035089]},
    "HACPC":      {"name": "Anonymous Contributors per Contributor",            "range": [0.2030862312030075, 0.6142201932899207]},
    "HRCPAC":     {"name": "Registered Contributor per Anonymous Contributor",  "range": [1.8360053180150566, 20.336666666666737]},
    "HREV":       {"name": "Revert Count",                                      "range": [11.0, 1194.0300000000007]},
    "HREVPR":     {"name": "Reverts per Review ",                               "range": [0.024020518790008875, 0.16390453763246082]},
    "HRML":       {"name": "Recent Review Diff ",                               "range": [0.0, 19805.26000000014]},
    "HREC":       {"name": "Recent Review Count",                               "range": [3.0, 257.0]},
    "HRECPR":     {"name": "Recent Reviews per Review",                         "range": [0.0049833887043189366, 0.36544712293174086]},
    "HACT":       {"name": "Active Review Count",                               "range": [230.0, 6216.02]},
    "HACTPR":     {"name": "Active Reviews per Review",                         "range": [0.4677335534671069, 0.8618585157443489]},
    "HOCCPR":     {"name": "Occasional Reviews per Review",                     "range": [0.3225806451612903, 0.6608631484099489]},
    "HSSLE":      {"name": "Seconds since Last Edit",                           "range": [1296000.0, 34564320.0000001]},
    "HMCL":       {"name": "Mean Comment Length",                               "range": [40.973408847067105, 64.29438592057762]}
}